{
 "chapter": 31,
 "title": "第三十一章 — 終章:凱旋歸來,黃金城最後的道別",
 "source_dat": "FDTXT_031",
 "location": "眾人平安傳送回馬拉大陸,慶幸保住了世界,彼此互道離別、各自展望歸程。返家途中索爾一行望見天空中最後一次浮現又永遠消失的黃金城,聽見悠妮的道別之聲。全劇最終以傳統「姓名:職業:」跑馬燈格式,逐一交代每位伙伴戰後的去向。",
 "notes": "本章「那是..悠妮最後的道別吧?」一段完整重現(且措辭與 FDTXT_027 章末片段幾乎相同),確認該重複片段確實是本章結局的完整版本,FDTXT_027 段落應視為劇本檔案的重疊/預覽殘留。「姓名:職業:」後方大段無對話框、無標點的整段文字為每位角色的傳統跑馬燈式旁白結局(仿 DQ 系列傳統),原始腳本無肖像代碼,均標記 speaker=-1、speaker_name「(旁白)」。",
 "scenes": [
  {
   "label": "凱旋,眾人互道珍重",
   "lines": [
    { "speaker": 3, "speaker_name": "哈瓦特", "text": "這是馬拉大陸的土地!我們終於又回到家園了。哈,多踩幾下這堅實的土地!" },
    { "speaker": 5, "speaker_name": "洛娜", "text": "啊~涼爽的微風,和煦的陽光!還是這個世界比較美好!" },
    { "speaker": 21, "speaker_name": "約拿", "text": "很高興我們解決了一切的事端,並且保住了這個世界。大家都做得很好!" },
    { "speaker": 8, "speaker_name": "希莉亞", "text": "我會叫父王辦個盛大的慶功宴,我們大家好好慶祝慶祝!這可是連王國禁衛軍都做不到的偉大成就哦!" },
    { "speaker": 5, "speaker_name": "洛娜", "text": "亞雷斯,到時候我們痛快的喝一杯!你會陪我的吧?" },
    { "speaker": 4, "speaker_name": "亞雷斯", "text": "這個..我負責在旅途中侍衛索爾王子,如今事情已經圓滿解決,為了避免陛下和皇后擔憂,我想還是早點回羅特帝亞比較好...." },
    { "speaker": 5, "speaker_name": "洛娜", "text": "這樣嗎..可是,可是......留下來玩個幾天不行嗎?" },
    { "speaker": 8, "speaker_name": "希莉亞", "text": "洛娜,既然你捨不得亞雷斯,可以和他一起回羅特帝亞啊!過幾天我也要以正式身份前往羅特帝亞拜訪,那時候妳再和我一起去不就好了。" },
    { "speaker": 5, "speaker_name": "洛娜", "text": "嗯,這樣的話,那.......亞雷斯,那我們到時候見了!" },
    { "speaker": 4, "speaker_name": "亞雷斯", "text": "嘿,好..好啊!唉!這下頭大了..." },
    { "speaker": 21, "speaker_name": "約拿", "text": "看到這些年輕人的樣子,真讓我想起自己年輕的時候。呵呵呵...." },
    { "speaker": 11, "speaker_name": "索菲亞", "text": "是啊!打贏了這麼一場仗,輕鬆輕鬆也是應該的..唉?索爾呢?" },
    { "speaker": 24, "speaker_name": "希爾法", "text": "怪了,剛剛還在這裡的....啊,在那邊!" },
    { "speaker": 4, "speaker_name": "亞雷斯", "text": "索爾,怎麼了?" },
    { "speaker": 0, "speaker_name": "索爾", "text": "悠妮..悠妮在那裡,在天空之中...." },
    { "speaker": 8, "speaker_name": "希莉亞", "text": "有嗎?我什麼都沒看到.." }
   ]
  },
  {
   "label": "黃金城最後的道別",
   "lines": [
    { "speaker": -1, "speaker_name": "(旁白)", "text": "那是..那是黃金城!" },
    { "speaker": -1, "speaker_name": "(旁白)", "text": "這就是幾百年來,從未有人見到過其廬山真面目的黃金城嗎?" },
    { "speaker": -1, "speaker_name": "(旁白)", "text": "....有著神與天空的威嚴,卻只能帶來死亡和毀滅的傳說之城...." },
    { "speaker": -1, "speaker_name": "(旁白)", "text": "....索爾....永遠再見了,你要好好保重...." },
    { "speaker": -1, "speaker_name": "(旁白)", "text": "是悠妮的聲音!悠妮...." },
    { "speaker": -1, "speaker_name": "(旁白)", "text": "那是....悠妮最後的道別吧?" },
    { "speaker": -1, "speaker_name": "(旁白)", "text": "....謝謝妳,悠妮!在往後的歲月中,我仍會永遠記得妳....和這段非凡的冒險旅程...." },
    { "speaker": -1, "speaker_name": "(旁白)", "text": "是的,一切就到此結束了。黃金城的傳說...." }
   ]
  },
  {
   "label": "尾聲:眾伙伴的後續",
   "lines": [
    { "speaker": -1, "speaker_name": "(旁白)", "text": "姓名:" },
    { "speaker": -1, "speaker_name": "(旁白)", "text": "職業:" },
    { "speaker": -1, "speaker_name": "(旁白)", "text": "在回程的路上,索爾默默的下了決心。為了悠妮的遺願,為了希莉亞的哀情,他要繼任羅特帝亞的王位,成為一個偉大的帝王。這是屬於他的宿命,不管自己的心中是多麼空虛...." },
    { "speaker": -1, "speaker_name": "(旁白)", "text": "和索爾一夥人度過無數艱險的哈諾,現在已被其父哈瓦那承認為一個真正的戰士了。據說父子倆正在建造船艦,準備一起前往某個傳說中的島嶼進行冒險。" },
    { "speaker": -1, "speaker_name": "(旁白)", "text": "在索爾一行的協助下,鐵諾終於化解了和王國軍的恩怨。心願已了之後,他決定離開這個傷心地繼續浪跡天涯。直到再有一天...." },
    { "speaker": -1, "speaker_name": "(旁白)", "text": "老而彌堅的哈瓦那是個閒不住的冒險者,聽說他最近找到一張祖傳的地圖,雀躍不已的準備要出海去尋寶。當然了,他的兒子哈諾會是他最得力的助手和伙伴。" },
    { "speaker": -1, "speaker_name": "(旁白)", "text": "完成了保護王子的使命之後,亞雷斯光榮的和索爾一起回國,隨即繼任禁衛騎士團長一職。他預期洛娜必會很快就追到這裡來,而且索爾會願意當這個現成的介紹人...." },
    { "speaker": -1, "speaker_name": "(旁白)", "text": "在索爾等人回國之後,身為騎士團代表的洛娜也喜孜孜的準備行李,等著和希莉亞一起前往羅特帝亞訪問。她身上帶著國王的親筆介紹信,這回亞雷斯是劫數難逃了...." },
    { "speaker": -1, "speaker_name": "(旁白)", "text": "萊汀仍任王國禁衛軍隊長一職。瑪爾的死解開了他心裏的死結,而莎拉的英姿則讓他找到了生命的另一個目標..這是讓眾人深深祝福的一對,雖然他們至今仍不肯承認。" },
    { "speaker": -1, "speaker_name": "(旁白)", "text": "這位沈默的騎士幾乎已被視為約拿的伙伴,所以當約拿在一個多霧的早晨飄然離去時,蘭斯洛特也隨著離開了。他的過去與一切,似乎比約拿還要神秘...." },
    { "speaker": -1, "speaker_name": "(旁白)", "text": "希莉亞雖然獲得了父王的應允,但索爾才剛受到悠妮離去的打擊,因此這回她出使羅特帝亞,將不會提起婚事。她相信,只要耐心的等,索爾總有一天會明白她的心意.." },
    { "speaker": -1, "speaker_name": "(旁白)", "text": "在漂浮在另一個時空的黃金城裏,悠妮在休眠艙裡沈睡著..等待著她的是另一段長久的沈眠,連她也不知道自己何時會再醒來。" },
    { "speaker": -1, "speaker_name": "(旁白)", "text": "自小嬌生慣養的瑪琳在這一番冒險之後,也終於有了些成長,現在她已是家中的乖女兒,不再恃嬌惹事,除了繼續僧侶神術的修行之外,她也已開始學著做些女紅家事。" },
    { "speaker": -1, "speaker_name": "(旁白)", "text": "身為大祭司的索菲亞在事件結束之後,還是回到了她所崇信的神的身邊。在亞克斯王國王城的神殿之中,光之神卡爾汀的祭壇之前,始終迴盪著她沈靜輕柔的祈禱聲...." },
    { "speaker": -1, "speaker_name": "(旁白)", "text": "在師兄賽可邦勒回到豹人族之後,就只剩凱麗陪在武神卡里斯身邊。她最近正因要與師父前往羅特帝亞而興奮不已,但若她知道師父此行的目的,可能就高興不起來了.." },
    { "speaker": -1, "speaker_name": "(旁白)", "text": "在事件之後,年輕的貝克威變得更加成熟了。他不願蟄居於故居的精靈族森林中,想要出去看看廣大的世界,因此事件結束後他就離開了,只有珊知道他的去處...." },
    { "speaker": -1, "speaker_name": "(旁白)", "text": "有感於在戰陣中自己在魔法技能上的不足,珊決定努力修習魔法。據說她和貝克威相約,當貝克威從外面歷練回來時,她就要成為一名真正的大法師。" },
    { "speaker": -1, "speaker_name": "(旁白)", "text": "告別了恩師卡里斯之後,賽可邦德回到了豹人族中,他現在不但是豹人族自衛隊的總教練,負責訓練年輕的豹人武士,也已經結婚生子,生活幸福美滿。" },
    { "speaker": -1, "speaker_name": "(旁白)", "text": "在與眾伙伴們打倒所有魔王後,凱拉斯終於報了昔日死在黑暗軍手下的部下們的血仇。在聖寇拉斯遷都平地之後,凱拉斯一直追隨其後,現在他擔任新都城守備軍的隊長。" },
    { "speaker": -1, "speaker_name": "(旁白)", "text": "憑著在激戰中所獲得的經驗與能力,米亞斯多德得以正式成為龍人族衛隊的一個隊長,他雖不時惦念過去自由的生活,但卻也能安於自己的新職位。" },
    { "speaker": -1, "speaker_name": "(旁白)", "text": "告別了眾位伙伴之後,蜜蒂回到了她的隱居之所,繼續劍術和心靈的修練。那個年輕人又在她沈靜的心湖裏掀起了一陣波瀾..但她相信,絕不會再有第三次了...." },
    { "speaker": -1, "speaker_name": "(旁白)", "text": "羅德曼在事件後便悄悄回到領地,以免擅離職守參與冒險之事被國王得知。但在希莉亞的多嘴之下,羅德曼仍被邀請往王城一行,痛快的和眾人舉行了一場慶功宴。" },
    { "speaker": -1, "speaker_name": "(旁白)", "text": "在宴會結束之後,莎拉迅即向眾人道別,然後乘上飛龍離去。她說她是要去尋找散落在大陸上的族人們,重新復興龍騎士一族。然而...." },
    { "speaker": -1, "speaker_name": "(旁白)", "text": "這位始終充滿了神秘的賢者在亞克斯王國作了幾天客之後,便向他的老友大法師希爾法道別,又開始了另一次新的旅程。當然,這次還是沒有人知道他們要到哪裡去...." },
    { "speaker": -1, "speaker_name": "(旁白)", "text": "武神卡里斯正準備結束多年來在馬拉大陸的旅程,返回故居羅特帝亞。據說他此行除了回故鄉定居外還另有目的,至於究竟是什麼目的就不得而知了。" },
    { "speaker": -1, "speaker_name": "(旁白)", "text": "身為精靈族的一員,羅蘭也隨著其他的族人們回到了森林中,她最近成為大法師希爾法的助手,大概是基於昔日的經驗,想在幫忙之餘順便學一些戰鬥用的魔法吧!" },
    { "speaker": -1, "speaker_name": "(旁白)", "text": "希爾法在事件結束後又開始了他的新課題,整天待在位於哈斯米爾的的新研究所裏,據說他正致力於時空魔法的研究,希望能再把黃金城帶回到這世界上來。" },
    { "speaker": -1, "speaker_name": "(旁白)", "text": "在戰鬥結束後,謝多又回到了黑森林,過著隱居的清閒生活。由於萊汀不時委託北上的商隊為他送去各種生活用品,謝多晚年的日子過得愉快而愜意。" },
    { "speaker": -1, "speaker_name": "(旁白)", "text": "為了興旺龍人一族,身為龍人族之王的聖寇拉斯決定將首都由高山遷到平地,並在亞克斯王國的協助下建立新的城市,相信龍人族必定會很快的昌盛起來。" },
    { "speaker": -1, "speaker_name": "(旁白)", "text": "由於他優越的武術和人品,禁衛軍隊長萊汀特地留巴拿羅西亞在亞克斯王國住下,平時他是龍人族在亞克斯王國的使節,也兼任禁衛軍的武術教練,和萊汀相處甚歡。" }
   ]
  }
 ]
}
