[
 {
  "map": 0,
  "chapter": 1,
  "turn_events": [
   {
    "turn": 3,
    "event_id": 0,
    "camp": "ally",
    "groups": [
     3,
     7
    ],
    "handler": "0x341db"
   },
   {
    "turn": 4,
    "event_id": 1,
    "camp": "enemy",
    "groups": [
     4
    ],
    "handler": "0x342b5"
   },
   {
    "turn": 5,
    "event_id": 2,
    "camp": "enemy",
    "groups": [
     5
    ],
    "handler": "0x3431d"
   },
   {
    "turn": 6,
    "event_id": 3,
    "camp": "ally",
    "groups": [
     6
    ],
    "handler": "0x34377"
   }
  ]
 },
 {
  "map": 1,
  "chapter": 2,
  "turn_events": [
   {
    "turn": 3,
    "event_id": 6,
    "camp": "ally",
    "groups": [
     3
    ],
    "handler": "0x34422"
   }
  ]
 },
 {
  "map": 2,
  "chapter": 3,
  "turn_events": [
   {
    "turn": 3,
    "event_id": 9,
    "camp": "special",
    "groups": [
     2
    ],
    "handler": "0x344c2"
   }
  ]
 },
 {
  "map": 3,
  "chapter": 4,
  "turn_events": [
   {
    "turn": 4,
    "event_id": 11,
    "camp": "ally",
    "groups": [
     2
    ],
    "handler": "0x34565"
   }
  ]
 },
 {
  "map": 4,
  "chapter": 5,
  "turn_events": [
   {
    "turn": 3,
    "event_id": 14,
    "camp": "enemy",
    "groups": [],
    "handler": "0x345ea"
   },
   {
    "turn": 4,
    "event_id": 15,
    "camp": "ally",
    "groups": [
     2
    ],
    "handler": "0x3462e"
   },
   {
    "turn": 7,
    "event_id": 16,
    "camp": "enemy",
    "groups": [
     3
    ],
    "handler": "0x34696"
   },
   {
    "turn": 8,
    "event_id": 17,
    "camp": "enemy",
    "groups": [],
    "handler": "0x346c8"
   }
  ]
 },
 {
  "map": 5,
  "chapter": 6,
  "turn_events": [
   {
    "turn": 5,
    "event_id": 20,
    "camp": "special",
    "groups": [],
    "handler": "0x347b1"
   },
   {
    "turn": 10,
    "event_id": 21,
    "camp": "special",
    "groups": [],
    "handler": "0x347d9"
   },
   {
    "turn": 15,
    "event_id": 22,
    "camp": "special",
    "groups": [
     1
    ],
    "handler": "0x34819"
   }
  ]
 },
 {
  "map": 6,
  "chapter": 7,
  "turn_events": [
   {
    "turn": 10,
    "event_id": 25,
    "camp": "enemy",
    "groups": [
     2
    ],
    "handler": "0x34924"
   }
  ]
 },
 {
  "map": 7,
  "chapter": 8,
  "turn_events": [
   {
    "turn": 2,
    "event_id": 27,
    "camp": "enemy",
    "groups": [
     "$turn_counter[0x53bef]"
    ],
    "handler": "0x349d9"
   },
   {
    "turn": 3,
    "event_id": 27,
    "camp": "enemy",
    "groups": [
     "$turn_counter[0x53bef]"
    ],
    "handler": "0x349d9"
   },
   {
    "turn": 4,
    "event_id": 27,
    "camp": "enemy",
    "groups": [
     "$turn_counter[0x53bef]"
    ],
    "handler": "0x349d9"
   },
   {
    "turn": 5,
    "event_id": 27,
    "camp": "enemy",
    "groups": [
     "$turn_counter[0x53bef]"
    ],
    "handler": "0x349d9"
   },
   {
    "turn": 6,
    "event_id": 27,
    "camp": "enemy",
    "groups": [
     "$turn_counter[0x53bef]"
    ],
    "handler": "0x349d9"
   },
   {
    "turn": 7,
    "event_id": 27,
    "camp": "enemy",
    "groups": [
     "$turn_counter[0x53bef]"
    ],
    "handler": "0x349d9"
   },
   {
    "turn": 15,
    "event_id": 28,
    "camp": "enemy",
    "groups": [],
    "handler": "0x34a0e"
   }
  ]
 },
 {
  "map": 8,
  "chapter": 9,
  "turn_events": []
 },
 {
  "map": 9,
  "chapter": 10,
  "turn_events": [
   {
    "turn": 5,
    "event_id": 32,
    "camp": "ally",
    "groups": [
     1
    ],
    "handler": "0x34be2"
   },
   {
    "turn": 20,
    "event_id": 33,
    "camp": "enemy",
    "groups": [],
    "handler": "0x34c1e"
   }
  ]
 },
 {
  "map": 10,
  "chapter": 11,
  "turn_events": []
 },
 {
  "map": 11,
  "chapter": 12,
  "turn_events": [
   {
    "turn": 1,
    "event_id": 35,
    "camp": "enemy",
    "groups": [
     2
    ],
    "handler": "0x34c76"
   },
   {
    "turn": 5,
    "event_id": 36,
    "camp": "ally",
    "groups": [],
    "handler": "0x34cb3"
   }
  ]
 },
 {
  "map": 12,
  "chapter": 13,
  "turn_events": [
   {
    "turn": 4,
    "event_id": 5,
    "camp": "ally",
    "groups": [],
    "handler": "0x34d68"
   },
   {
    "turn": 9,
    "event_id": 7,
    "camp": "enemy",
    "groups": [
     2
    ],
    "handler": "0x34d72"
   }
  ]
 },
 {
  "map": 13,
  "chapter": 14,
  "turn_events": []
 },
 {
  "map": 14,
  "chapter": 15,
  "turn_events": [
   {
    "turn": 4,
    "event_id": 13,
    "camp": "ally",
    "groups": [],
    "handler": "0x34e90"
   },
   {
    "turn": 9,
    "event_id": 18,
    "camp": "enemy",
    "groups": [],
    "handler": "0x34f02"
   },
   {
    "turn": 7,
    "event_id": 38,
    "camp": "enemy",
    "groups": [
     1
    ],
    "handler": "0x34f42"
   }
  ]
 },
 {
  "map": 15,
  "chapter": 16,
  "turn_events": []
 },
 {
  "map": 16,
  "chapter": 17,
  "turn_events": [
   {
    "turn": 4,
    "event_id": 40,
    "camp": "ally",
    "groups": [
     2
    ],
    "handler": "0x34fcb"
   }
  ]
 },
 {
  "map": 17,
  "chapter": 18,
  "turn_events": [
   {
    "turn": 3,
    "event_id": 43,
    "camp": "enemy",
    "groups": [],
    "handler": "0x35091"
   },
   {
    "turn": 8,
    "event_id": 42,
    "camp": "enemy",
    "groups": [
     1
    ],
    "handler": "0x3505f"
   }
  ]
 },
 {
  "map": 18,
  "chapter": 19,
  "turn_events": [
   {
    "turn": 4,
    "event_id": 44,
    "camp": "special",
    "groups": [],
    "handler": "0x350a4"
   },
   {
    "turn": 6,
    "event_id": 46,
    "camp": "ally",
    "groups": [
     1
    ],
    "handler": "0x350cc"
   },
   {
    "turn": 10,
    "event_id": 45,
    "camp": "special",
    "groups": [],
    "handler": "0x350b9"
   }
  ]
 },
 {
  "map": 19,
  "chapter": 20,
  "turn_events": []
 },
 {
  "map": 20,
  "chapter": 21,
  "turn_events": [
   {
    "turn": 2,
    "event_id": 47,
    "camp": "enemy",
    "groups": [
     1
    ],
    "handler": "0x35112",
    "group_formula": "floor(turn_counter/2) via signed-div-by-2 idiom at handler+0x0a..0x12 (edx=eax>>31;eax-=edx;eax>>=1), eax=[0x53bef] turn counter"
   },
   {
    "turn": 3,
    "event_id": 48,
    "camp": "enemy",
    "groups": [],
    "handler": "0x351c6"
   },
   {
    "turn": 4,
    "event_id": 47,
    "camp": "enemy",
    "groups": [
     2
    ],
    "handler": "0x35112",
    "group_formula": "floor(turn_counter/2) via signed-div-by-2 idiom at handler+0x0a..0x12 (edx=eax>>31;eax-=edx;eax>>=1), eax=[0x53bef] turn counter"
   },
   {
    "turn": 6,
    "event_id": 47,
    "camp": "enemy",
    "groups": [
     3
    ],
    "handler": "0x35112",
    "group_formula": "floor(turn_counter/2) via signed-div-by-2 idiom at handler+0x0a..0x12 (edx=eax>>31;eax-=edx;eax>>=1), eax=[0x53bef] turn counter"
   },
   {
    "turn": 8,
    "event_id": 47,
    "camp": "enemy",
    "groups": [
     4
    ],
    "handler": "0x35112",
    "group_formula": "floor(turn_counter/2) via signed-div-by-2 idiom at handler+0x0a..0x12 (edx=eax>>31;eax-=edx;eax>>=1), eax=[0x53bef] turn counter"
   }
  ]
 },
 {
  "map": 21,
  "chapter": 22,
  "turn_events": [
   {
    "turn": 3,
    "event_id": 49,
    "camp": "enemy",
    "groups": [
     1
    ],
    "handler": "0x351e9",
    "group_formula": "floor(turn_counter/2) via signed-div-by-2 idiom at handler+0x0a..0x12 (edx=eax>>31;eax-=edx;eax>>=1), eax=[0x53bef] turn counter"
   },
   {
    "turn": 5,
    "event_id": 50,
    "camp": "special",
    "groups": [
     2
    ],
    "handler": "0x35261"
   },
   {
    "turn": 7,
    "event_id": 49,
    "camp": "enemy",
    "groups": [
     3
    ],
    "handler": "0x351e9",
    "group_formula": "floor(turn_counter/2) via signed-div-by-2 idiom at handler+0x0a..0x12 (edx=eax>>31;eax-=edx;eax>>=1), eax=[0x53bef] turn counter"
   }
  ]
 },
 {
  "map": 22,
  "chapter": 23,
  "turn_events": [
   {
    "turn": 13,
    "event_id": 52,
    "camp": "enemy",
    "groups": [],
    "handler": "0x352e2"
   },
   {
    "turn": 15,
    "event_id": 52,
    "camp": "enemy",
    "groups": [],
    "handler": "0x352e2"
   },
   {
    "turn": 18,
    "event_id": 52,
    "camp": "enemy",
    "groups": [],
    "handler": "0x352e2"
   },
   {
    "turn": 22,
    "event_id": 52,
    "camp": "enemy",
    "groups": [],
    "handler": "0x352e2"
   }
  ]
 },
 {
  "map": 23,
  "chapter": 24,
  "turn_events": [
   {
    "turn": 2,
    "event_id": 54,
    "camp": "enemy",
    "groups": [
     "$turn_counter[0x53bef]"
    ],
    "handler": "0x3535d"
   },
   {
    "turn": 4,
    "event_id": 54,
    "camp": "enemy",
    "groups": [
     "$turn_counter[0x53bef]"
    ],
    "handler": "0x3535d"
   },
   {
    "turn": 7,
    "event_id": 54,
    "camp": "enemy",
    "groups": [
     "$turn_counter[0x53bef]"
    ],
    "handler": "0x3535d"
   },
   {
    "turn": 10,
    "event_id": 54,
    "camp": "enemy",
    "groups": [
     "$turn_counter[0x53bef]"
    ],
    "handler": "0x3535d"
   }
  ]
 },
 {
  "map": 24,
  "chapter": 25,
  "turn_events": [
   {
    "turn": 6,
    "event_id": 56,
    "camp": "ally",
    "groups": [
     1
    ],
    "handler": "0x35487"
   }
  ]
 },
 {
  "map": 25,
  "chapter": 26,
  "turn_events": [
   {
    "turn": 2,
    "event_id": 57,
    "camp": "enemy",
    "groups": [
     "$turn_counter[0x53bef]"
    ],
    "handler": "0x354dd"
   },
   {
    "turn": 4,
    "event_id": 57,
    "camp": "enemy",
    "groups": [
     "$turn_counter[0x53bef]"
    ],
    "handler": "0x354dd"
   },
   {
    "turn": 6,
    "event_id": 57,
    "camp": "enemy",
    "groups": [
     "$turn_counter[0x53bef]"
    ],
    "handler": "0x354dd"
   },
   {
    "turn": 8,
    "event_id": 57,
    "camp": "enemy",
    "groups": [
     "$turn_counter[0x53bef]"
    ],
    "handler": "0x354dd"
   },
   {
    "turn": 10,
    "event_id": 57,
    "camp": "enemy",
    "groups": [
     "$turn_counter[0x53bef]"
    ],
    "handler": "0x354dd"
   },
   {
    "turn": 12,
    "event_id": 57,
    "camp": "enemy",
    "groups": [
     "$turn_counter[0x53bef]"
    ],
    "handler": "0x354dd"
   },
   {
    "turn": 15,
    "event_id": 57,
    "camp": "enemy",
    "groups": [
     "$turn_counter[0x53bef]"
    ],
    "handler": "0x354dd"
   },
   {
    "turn": 16,
    "event_id": 57,
    "camp": "enemy",
    "groups": [
     "$turn_counter[0x53bef]"
    ],
    "handler": "0x354dd"
   },
   {
    "turn": 17,
    "event_id": 57,
    "camp": "enemy",
    "groups": [
     "$turn_counter[0x53bef]"
    ],
    "handler": "0x354dd"
   }
  ]
 },
 {
  "map": 26,
  "chapter": 27,
  "turn_events": []
 },
 {
  "map": 27,
  "chapter": 28,
  "turn_events": []
 },
 {
  "map": 28,
  "chapter": 29,
  "turn_events": []
 },
 {
  "map": 29,
  "chapter": 30,
  "turn_events": []
 }
]